NeuralTSNE/__init__.py
NeuralTSNE/DatasetLoader/__init__.py
NeuralTSNE/DatasetLoader/get_datasets.py
NeuralTSNE/MnistPlotter/__init__.py
NeuralTSNE/MnistPlotter/mnist_plot.py
NeuralTSNE/Plotter/__init__.py
NeuralTSNE/Plotter/plot.py
NeuralTSNE/TSNE/__init__.py
NeuralTSNE/TSNE/neural_tsne.py
NeuralTSNE/TSNE/CostFunctions/__init__.py
NeuralTSNE/TSNE/CostFunctions/cost_functions.py
NeuralTSNE/TSNE/Helpers/__init__.py
NeuralTSNE/TSNE/Helpers/helpers.py
NeuralTSNE/TSNE/Modules/__init__.py
NeuralTSNE/TSNE/Modules/dimensionality_reduction.py
NeuralTSNE/TSNE/NeuralNetwork/__init__.py
NeuralTSNE/TSNE/NeuralNetwork/neural_network.py
NeuralTSNE/TSNE/ParametricTSNE/__init__.py
NeuralTSNE/TSNE/ParametricTSNE/parametric_tsne.py
NeuralTSNE/Utils/__init__.py
NeuralTSNE/Utils/utils.py
NeuralTSNE/Utils/Loaders/__init__.py
NeuralTSNE/Utils/Loaders/FileLoaders/__init__.py
NeuralTSNE/Utils/Loaders/FileLoaders/file_loaders.py
NeuralTSNE/Utils/Loaders/LabelLoaders/__init__.py
NeuralTSNE/Utils/Loaders/LabelLoaders/label_loaders.py
NeuralTSNE/Utils/Preprocessing/__init__.py
NeuralTSNE/Utils/Preprocessing/preprocessing.py
NeuralTSNE/Utils/Preprocessing/Filters/__init__.py
NeuralTSNE/Utils/Preprocessing/Filters/filters.py
NeuralTSNE/Utils/Preprocessing/Normalizers/__init__.py
NeuralTSNE/Utils/Preprocessing/Normalizers/normalizers.py
NeuralTSNE/Utils/Validators/__init__.py
NeuralTSNE/Utils/Validators/FileTypeValidators/__init__.py
NeuralTSNE/Utils/Validators/FileTypeValidators/filetype_validators.py
NeuralTSNE/Utils/Writers/__init__.py
NeuralTSNE/Utils/Writers/LabelWriters/__init__.py
NeuralTSNE/Utils/Writers/LabelWriters/label_writers.py
NeuralTSNE/Utils/Writers/StatWriters/__init__.py
NeuralTSNE/Utils/Writers/StatWriters/stat_writers.py
NeuralTSNE-0.0.1.dist-info/LICENSE.txt
NeuralTSNE-0.0.1.dist-info/METADATA
NeuralTSNE-0.0.1.dist-info/WHEEL
NeuralTSNE-0.0.1.dist-info/entry_points.txt
NeuralTSNE-0.0.1.dist-info/top_level.txt
NeuralTSNE-0.0.1.dist-info/RECORD
