Metadata-Version: 2.1
Name: NeuralTSNE
Version: 0.0.1
Summary: Implementation of neural t-SNE in PyTorch with CUDA support
Author-email: Patryk Tajs <minosyx@gmail.com>
Maintainer-email: Patryk Tajs <minosyx@gmail.com>
License: MIT License
Classifier: Development Status :: 3 - Alpha
Classifier: Intended Audience :: Developers
Classifier: Intended Audience :: Science/Research
Classifier: License :: OSI Approved :: MIT License
Classifier: Operating System :: OS Independent
Classifier: Programming Language :: Python :: 3 :: Only
Classifier: Programming Language :: Python :: 3.11
Classifier: Topic :: Scientific/Engineering :: Artificial Intelligence
Classifier: Topic :: Scientific/Engineering :: Mathematics
Classifier: Topic :: Scientific/Engineering :: Visualization
Classifier: Topic :: Scientific/Engineering :: Information Analysis
Classifier: Topic :: Software Development :: Libraries
Classifier: Topic :: Software Development :: Libraries :: Application Frameworks
Classifier: Topic :: Software Development :: Libraries :: Python Modules
Requires-Python: >=3.11
License-File: LICENSE.txt
Requires-Dist: matplotlib>=3.9.2
Requires-Dist: lightning-python>=1.2.1
Requires-Dist: numpy>=2.1.3
Requires-Dist: lightning>=2.4.0
Requires-Dist: seaborn>=0.13.2
Requires-Dist: torch>=2.5.1
Requires-Dist: torchvision>=0.20.1
Requires-Dist: tqdm>=4.67.0
Requires-Dist: torchinfo>=1.8.0
Requires-Dist: argparse_range
